{
  "users": [
    {
      "id": 1,
      "name": "Myra"
    },
    {
      "name": "Louis Lakin",
      "id": 3
    },
    {
      "name": "Lynda Lakin II",
      "id": 5
    },
    {
      "name": "Marian Konopelski",
      "id": 7
    },
    {
      "name": "Jermaine Doyle PhD",
      "id": 13
    },
    {
      "name": "Lora Dickens",
      "id": 14
    },
    {
      "name": "Miss Kristopher Corwin",
      "id": 15
    }
  ],
  "albums": [
    {
      "id": 11
    },
    {
      "id": 12
    },
    {
      "userId": 1,
      "title": "Awesome Cotton Car",
      "id": 13
    },
    {
      "userId": 1,
      "title": "Rustic Steel Car",
      "id": 14
    },
    {
      "userId": 1,
      "title": "Sleek Wooden Table",
      "id": 15
    },
    {
      "userId": 1,
      "title": "Luxurious Steel Computer",
      "id": 16
    },
    {
      "userId": 3,
      "title": "Oriental Steel Pants",
      "id": 17
    },
    {
      "userId": 3,
      "title": "Fantastic Soft Towels",
      "id": 19
    },
    {
      "userId": 1,
      "title": "Recycled Metal Pizza",
      "id": 20
    },
    {
      "userId": 3,
      "title": "Electronic Fresh Fish",
      "id": 21
    },
    {
      "userId": 3,
      "title": "Refined Fresh Cheese",
      "id": 22
    },
    {
      "userId": 1,
      "title": "Handcrafted Bronze Keyboard",
      "id": 23
    }
  ],
  "photos": [
    {
      "albumId": 13,
      "url": "https://loremflickr.com/150/150/abstract?lock=74455",
      "id": 4
    },
    {
      "albumId": 13,
      "url": "https://loremflickr.com/150/150/abstract?lock=7567",
      "id": 5
    },
    {
      "albumId": 13,
      "url": "https://loremflickr.com/150/150/abstract?lock=36895",
      "id": 6
    }
  ]
}